{"nodes": [{"id": "a_unversidad_practicas_uni_codigo_soea_src_soea_domain_entities_bloquetiempo_cs", "label": "BloqueTiempo.cs", "file_type": "code", "source_file": "A:\\Unversidad\\_PRACTICAS_UNI\\CODIGO\\SOEA\\src\\SOEA.Domain\\Entities\\BloqueTiempo.cs", "source_location": "L1"}, {"id": "entities_bloquetiempo_soea_domain_entities", "label": "SOEA.Domain.Entities", "file_type": "code", "source_file": "A:\\Unversidad\\_PRACTICAS_UNI\\CODIGO\\SOEA\\src\\SOEA.Domain\\Entities\\BloqueTiempo.cs", "source_location": "L4"}, {"id": "entities_bloquetiempo_bloquetiempo", "label": "BloqueTiempo", "file_type": "code", "source_file": "A:\\Unversidad\\_PRACTICAS_UNI\\CODIGO\\SOEA\\src\\SOEA.Domain\\Entities\\BloqueTiempo.cs", "source_location": "L11"}, {"id": "entidadbase", "label": "EntidadBase", "file_type": "code", "source_file": "", "source_location": ""}, {"id": "entities_bloquetiempo_bloquetiempo_validar", "label": ".Validar()", "file_type": "code", "source_file": "A:\\Unversidad\\_PRACTICAS_UNI\\CODIGO\\SOEA\\src\\SOEA.Domain\\Entities\\BloqueTiempo.cs", "source_location": "L45"}, {"id": "diadesemana", "label": "DiaDeSemana", "file_type": "code", "source_file": "A:\\Unversidad\\_PRACTICAS_UNI\\CODIGO\\SOEA\\src\\SOEA.Domain\\Entities\\BloqueTiempo.cs", "source_location": "L45"}, {"id": "timeonly", "label": "TimeOnly", "file_type": "code", "source_file": "A:\\Unversidad\\_PRACTICAS_UNI\\CODIGO\\SOEA\\src\\SOEA.Domain\\Entities\\BloqueTiempo.cs", "source_location": "L45"}], "edges": [{"source": "a_unversidad_practicas_uni_codigo_soea_src_soea_domain_entities_bloquetiempo_cs", "target": "system", "relation": "imports", "context": "import", "confidence": "EXTRACTED", "source_file": "A:\\Unversidad\\_PRACTICAS_UNI\\CODIGO\\SOEA\\src\\SOEA.Domain\\Entities\\BloqueTiempo.cs", "source_location": "L1", "weight": 1.0}, {"source": "a_unversidad_practicas_uni_codigo_soea_src_soea_domain_entities_bloquetiempo_cs", "target": "enums", "relation": "imports", "context": "import", "confidence": "EXTRACTED", "source_file": "A:\\Unversidad\\_PRACTICAS_UNI\\CODIGO\\SOEA\\src\\SOEA.Domain\\Entities\\BloqueTiempo.cs", "source_location": "L2", "weight": 1.0}, {"source": "a_unversidad_practicas_uni_codigo_soea_src_soea_domain_entities_bloquetiempo_cs", "target": "entities_bloquetiempo_soea_domain_entities", "relation": "contains", "confidence": "EXTRACTED", "source_file": "A:\\Unversidad\\_PRACTICAS_UNI\\CODIGO\\SOEA\\src\\SOEA.Domain\\Entities\\BloqueTiempo.cs", "source_location": "L4", "weight": 1.0}, {"source": "a_unversidad_practicas_uni_codigo_soea_src_soea_domain_entities_bloquetiempo_cs", "target": "entities_bloquetiempo_bloquetiempo", "relation": "contains", "confidence": "EXTRACTED", "source_file": "A:\\Unversidad\\_PRACTICAS_UNI\\CODIGO\\SOEA\\src\\SOEA.Domain\\Entities\\BloqueTiempo.cs", "source_location": "L11", "weight": 1.0}, {"source": "entities_bloquetiempo_bloquetiempo", "target": "entidadbase", "relation": "inherits", "confidence": "EXTRACTED", "source_file": "A:\\Unversidad\\_PRACTICAS_UNI\\CODIGO\\SOEA\\src\\SOEA.Domain\\Entities\\BloqueTiempo.cs", "source_location": "L11", "weight": 1.0}, {"source": "entities_bloquetiempo_bloquetiempo", "target": "entities_bloquetiempo_bloquetiempo_validar", "relation": "method", "confidence": "EXTRACTED", "source_file": "A:\\Unversidad\\_PRACTICAS_UNI\\CODIGO\\SOEA\\src\\SOEA.Domain\\Entities\\BloqueTiempo.cs", "source_location": "L45", "weight": 1.0}, {"source": "entities_bloquetiempo_bloquetiempo_validar", "target": "diadesemana", "relation": "references", "confidence": "EXTRACTED", "source_file": "A:\\Unversidad\\_PRACTICAS_UNI\\CODIGO\\SOEA\\src\\SOEA.Domain\\Entities\\BloqueTiempo.cs", "source_location": "L45", "weight": 1.0, "context": "parameter_type"}, {"source": "entities_bloquetiempo_bloquetiempo_validar", "target": "timeonly", "relation": "references", "confidence": "EXTRACTED", "source_file": "A:\\Unversidad\\_PRACTICAS_UNI\\CODIGO\\SOEA\\src\\SOEA.Domain\\Entities\\BloqueTiempo.cs", "source_location": "L45", "weight": 1.0, "context": "parameter_type"}, {"source": "entities_bloquetiempo_bloquetiempo_validar", "target": "timeonly", "relation": "references", "confidence": "EXTRACTED", "source_file": "A:\\Unversidad\\_PRACTICAS_UNI\\CODIGO\\SOEA\\src\\SOEA.Domain\\Entities\\BloqueTiempo.cs", "source_location": "L45", "weight": 1.0, "context": "parameter_type"}], "raw_calls": []}