{"nodes": [{"id": "a_unversidad_practicas_uni_codigo_soea_src_soea_engine_constraintprog_motorconstraintprogramming_cs", "label": "MotorConstraintProgramming.cs", "file_type": "code", "source_file": "A:\\Unversidad\\_PRACTICAS_UNI\\CODIGO\\SOEA\\src\\SOEA.Engine.ConstraintProg\\MotorConstraintProgramming.cs", "source_location": "L1"}, {"id": "soea_engine_constraintprog_motorconstraintprogramming_soea_engine_constraintprog", "label": "SOEA.Engine.ConstraintProg", "file_type": "code", "source_file": "A:\\Unversidad\\_PRACTICAS_UNI\\CODIGO\\SOEA\\src\\SOEA.Engine.ConstraintProg\\MotorConstraintProgramming.cs", "source_location": "L13"}, {"id": "soea_engine_constraintprog_motorconstraintprogramming_motorconstraintprogramming", "label": "MotorConstraintProgramming", "file_type": "code", "source_file": "A:\\Unversidad\\_PRACTICAS_UNI\\CODIGO\\SOEA\\src\\SOEA.Engine.ConstraintProg\\MotorConstraintProgramming.cs", "source_location": "L24"}, {"id": "imotorconstraintprogramming", "label": "IMotorConstraintProgramming", "file_type": "code", "source_file": "", "source_location": ""}, {"id": "ilogger", "label": "ILogger", "file_type": "code", "source_file": "A:\\Unversidad\\_PRACTICAS_UNI\\CODIGO\\SOEA\\src\\SOEA.Engine.ConstraintProg\\MotorConstraintProgramming.cs", "source_location": "L26"}, {"id": "int", "label": "int", "file_type": "code", "source_file": "A:\\Unversidad\\_PRACTICAS_UNI\\CODIGO\\SOEA\\src\\SOEA.Engine.ConstraintProg\\MotorConstraintProgramming.cs", "source_location": "L27"}, {"id": "semanaacademica", "label": "SemanaAcademica", "file_type": "code", "source_file": "A:\\Unversidad\\_PRACTICAS_UNI\\CODIGO\\SOEA\\src\\SOEA.Engine.ConstraintProg\\MotorConstraintProgramming.cs", "source_location": "L29"}, {"id": "soea_engine_constraintprog_motorconstraintprogramming_motorconstraintprogramming_resolverfactibilidadasync", "label": ".ResolverFactibilidadAsync()", "file_type": "code", "source_file": "A:\\Unversidad\\_PRACTICAS_UNI\\CODIGO\\SOEA\\src\\SOEA.Engine.ConstraintProg\\MotorConstraintProgramming.cs", "source_location": "L36"}, {"id": "ienumerable", "label": "IEnumerable", "file_type": "code", "source_file": "A:\\Unversidad\\_PRACTICAS_UNI\\CODIGO\\SOEA\\src\\SOEA.Engine.ConstraintProg\\MotorConstraintProgramming.cs", "source_location": "L36"}, {"id": "sesion", "label": "Sesion", "file_type": "code", "source_file": "A:\\Unversidad\\_PRACTICAS_UNI\\CODIGO\\SOEA\\src\\SOEA.Engine.ConstraintProg\\MotorConstraintProgramming.cs", "source_location": "L36"}, {"id": "bloquetiempo", "label": "BloqueTiempo", "file_type": "code", "source_file": "A:\\Unversidad\\_PRACTICAS_UNI\\CODIGO\\SOEA\\src\\SOEA.Engine.ConstraintProg\\MotorConstraintProgramming.cs", "source_location": "L36"}, {"id": "espacio", "label": "Espacio", "file_type": "code", "source_file": "A:\\Unversidad\\_PRACTICAS_UNI\\CODIGO\\SOEA\\src\\SOEA.Engine.ConstraintProg\\MotorConstraintProgramming.cs", "source_location": "L36"}, {"id": "docente", "label": "Docente", "file_type": "code", "source_file": "A:\\Unversidad\\_PRACTICAS_UNI\\CODIGO\\SOEA\\src\\SOEA.Engine.ConstraintProg\\MotorConstraintProgramming.cs", "source_location": "L36"}, {"id": "task", "label": "Task", "file_type": "code", "source_file": "A:\\Unversidad\\_PRACTICAS_UNI\\CODIGO\\SOEA\\src\\SOEA.Engine.ConstraintProg\\MotorConstraintProgramming.cs", "source_location": "L36"}, {"id": "resultadofactibilidad", "label": "ResultadoFactibilidad", "file_type": "code", "source_file": "A:\\Unversidad\\_PRACTICAS_UNI\\CODIGO\\SOEA\\src\\SOEA.Engine.ConstraintProg\\MotorConstraintProgramming.cs", "source_location": "L36"}, {"id": "soea_engine_constraintprog_motorconstraintprogramming_motorconstraintprogramming_modalidadde", "label": ".ModalidadDe()", "file_type": "code", "source_file": "A:\\Unversidad\\_PRACTICAS_UNI\\CODIGO\\SOEA\\src\\SOEA.Engine.ConstraintProg\\MotorConstraintProgramming.cs", "source_location": "L51"}, {"id": "modalidad", "label": "Modalidad", "file_type": "code", "source_file": "A:\\Unversidad\\_PRACTICAS_UNI\\CODIGO\\SOEA\\src\\SOEA.Engine.ConstraintProg\\MotorConstraintProgramming.cs", "source_location": "L51"}, {"id": "soea_engine_constraintprog_motorconstraintprogramming_motorconstraintprogramming_resolversincrono", "label": ".ResolverSincrono()", "file_type": "code", "source_file": "A:\\Unversidad\\_PRACTICAS_UNI\\CODIGO\\SOEA\\src\\SOEA.Engine.ConstraintProg\\MotorConstraintProgramming.cs", "source_location": "L66"}, {"id": "list", "label": "List", "file_type": "code", "source_file": "A:\\Unversidad\\_PRACTICAS_UNI\\CODIGO\\SOEA\\src\\SOEA.Engine.ConstraintProg\\MotorConstraintProgramming.cs", "source_location": "L66"}], "edges": [{"source": "a_unversidad_practicas_uni_codigo_soea_src_soea_engine_constraintprog_motorconstraintprogramming_cs", "target": "system", "relation": "imports", "context": "import", "confidence": "EXTRACTED", "source_file": "A:\\Unversidad\\_PRACTICAS_UNI\\CODIGO\\SOEA\\src\\SOEA.Engine.ConstraintProg\\MotorConstraintProgramming.cs", "source_location": "L1", "weight": 1.0}, {"source": "a_unversidad_practicas_uni_codigo_soea_src_soea_engine_constraintprog_motorconstraintprogramming_cs", "target": "generic", "relation": "imports", "context": "import", "confidence": "EXTRACTED", "source_file": "A:\\Unversidad\\_PRACTICAS_UNI\\CODIGO\\SOEA\\src\\SOEA.Engine.ConstraintProg\\MotorConstraintProgramming.cs", "source_location": "L2", "weight": 1.0}, {"source": "a_unversidad_practicas_uni_codigo_soea_src_soea_engine_constraintprog_motorconstraintprogramming_cs", "target": "linq", "relation": "imports", "context": "import", "confidence": "EXTRACTED", "source_file": "A:\\Unversidad\\_PRACTICAS_UNI\\CODIGO\\SOEA\\src\\SOEA.Engine.ConstraintProg\\MotorConstraintProgramming.cs", "source_location": "L3", "weight": 1.0}, {"source": "a_unversidad_practicas_uni_codigo_soea_src_soea_engine_constraintprog_motorconstraintprogramming_cs", "target": "tasks", "relation": "imports", "context": "import", "confidence": "EXTRACTED", "source_file": "A:\\Unversidad\\_PRACTICAS_UNI\\CODIGO\\SOEA\\src\\SOEA.Engine.ConstraintProg\\MotorConstraintProgramming.cs", "source_location": "L4", "weight": 1.0}, {"source": "a_unversidad_practicas_uni_codigo_soea_src_soea_engine_constraintprog_motorconstraintprogramming_cs", "target": "sat", "relation": "imports", "context": "import", "confidence": "EXTRACTED", "source_file": "A:\\Unversidad\\_PRACTICAS_UNI\\CODIGO\\SOEA\\src\\SOEA.Engine.ConstraintProg\\MotorConstraintProgramming.cs", "source_location": "L5", "weight": 1.0}, {"source": "a_unversidad_practicas_uni_codigo_soea_src_soea_engine_constraintprog_motorconstraintprogramming_cs", "target": "logging", "relation": "imports", "context": "import", "confidence": "EXTRACTED", "source_file": "A:\\Unversidad\\_PRACTICAS_UNI\\CODIGO\\SOEA\\src\\SOEA.Engine.ConstraintProg\\MotorConstraintProgramming.cs", "source_location": "L6", "weight": 1.0}, {"source": "a_unversidad_practicas_uni_codigo_soea_src_soea_engine_constraintprog_motorconstraintprogramming_cs", "target": "entities", "relation": "imports", "context": "import", "confidence": "EXTRACTED", "source_file": "A:\\Unversidad\\_PRACTICAS_UNI\\CODIGO\\SOEA\\src\\SOEA.Engine.ConstraintProg\\MotorConstraintProgramming.cs", "source_location": "L7", "weight": 1.0}, {"source": "a_unversidad_practicas_uni_codigo_soea_src_soea_engine_constraintprog_motorconstraintprogramming_cs", "target": "enums", "relation": "imports", "context": "import", "confidence": "EXTRACTED", "source_file": "A:\\Unversidad\\_PRACTICAS_UNI\\CODIGO\\SOEA\\src\\SOEA.Engine.ConstraintProg\\MotorConstraintProgramming.cs", "source_location": "L8", "weight": 1.0}, {"source": "a_unversidad_practicas_uni_codigo_soea_src_soea_engine_constraintprog_motorconstraintprogramming_cs", "target": "interfaces", "relation": "imports", "context": "import", "confidence": "EXTRACTED", "source_file": "A:\\Unversidad\\_PRACTICAS_UNI\\CODIGO\\SOEA\\src\\SOEA.Engine.ConstraintProg\\MotorConstraintProgramming.cs", "source_location": "L9", "weight": 1.0}, {"source": "a_unversidad_practicas_uni_codigo_soea_src_soea_engine_constraintprog_motorconstraintprogramming_cs", "target": "services", "relation": "imports", "context": "import", "confidence": "EXTRACTED", "source_file": "A:\\Unversidad\\_PRACTICAS_UNI\\CODIGO\\SOEA\\src\\SOEA.Engine.ConstraintProg\\MotorConstraintProgramming.cs", "source_location": "L10", "weight": 1.0}, {"source": "a_unversidad_practicas_uni_codigo_soea_src_soea_engine_constraintprog_motorconstraintprogramming_cs", "target": "cpdomain", "relation": "imports", "context": "import", "confidence": "EXTRACTED", "source_file": "A:\\Unversidad\\_PRACTICAS_UNI\\CODIGO\\SOEA\\src\\SOEA.Engine.ConstraintProg\\MotorConstraintProgramming.cs", "source_location": "L11", "weight": 1.0}, {"source": "a_unversidad_practicas_uni_codigo_soea_src_soea_engine_constraintprog_motorconstraintprogramming_cs", "target": "soea_engine_constraintprog_motorconstraintprogramming_soea_engine_constraintprog", "relation": "contains", "confidence": "EXTRACTED", "source_file": "A:\\Unversidad\\_PRACTICAS_UNI\\CODIGO\\SOEA\\src\\SOEA.Engine.ConstraintProg\\MotorConstraintProgramming.cs", "source_location": "L13", "weight": 1.0}, {"source": "a_unversidad_practicas_uni_codigo_soea_src_soea_engine_constraintprog_motorconstraintprogramming_cs", "target": "soea_engine_constraintprog_motorconstraintprogramming_motorconstraintprogramming", "relation": "contains", "confidence": "EXTRACTED", "source_file": "A:\\Unversidad\\_PRACTICAS_UNI\\CODIGO\\SOEA\\src\\SOEA.Engine.ConstraintProg\\MotorConstraintProgramming.cs", "source_location": "L24", "weight": 1.0}, {"source": "soea_engine_constraintprog_motorconstraintprogramming_motorconstraintprogramming", "target": "imotorconstraintprogramming", "relation": "implements", "confidence": "EXTRACTED", "source_file": "A:\\Unversidad\\_PRACTICAS_UNI\\CODIGO\\SOEA\\src\\SOEA.Engine.ConstraintProg\\MotorConstraintProgramming.cs", "source_location": "L24", "weight": 1.0}, {"source": "soea_engine_constraintprog_motorconstraintprogramming_motorconstraintprogramming", "target": "ilogger", "relation": "references", "confidence": "EXTRACTED", "source_file": "A:\\Unversidad\\_PRACTICAS_UNI\\CODIGO\\SOEA\\src\\SOEA.Engine.ConstraintProg\\MotorConstraintProgramming.cs", "source_location": "L26", "weight": 1.0, "context": "field"}, {"source": "soea_engine_constraintprog_motorconstraintprogramming_motorconstraintprogramming", "target": "int", "relation": "references", "confidence": "EXTRACTED", "source_file": "A:\\Unversidad\\_PRACTICAS_UNI\\CODIGO\\SOEA\\src\\SOEA.Engine.ConstraintProg\\MotorConstraintProgramming.cs", "source_location": "L27", "weight": 1.0, "context": "field"}, {"source": "soea_engine_constraintprog_motorconstraintprogramming_motorconstraintprogramming", "target": "semanaacademica", "relation": "references", "confidence": "EXTRACTED", "source_file": "A:\\Unversidad\\_PRACTICAS_UNI\\CODIGO\\SOEA\\src\\SOEA.Engine.ConstraintProg\\MotorConstraintProgramming.cs", "source_location": "L29", "weight": 1.0, "context": "field"}, {"source": "soea_engine_constraintprog_motorconstraintprogramming_motorconstraintprogramming", "target": "soea_engine_constraintprog_motorconstraintprogramming_motorconstraintprogramming_resolverfactibilidadasync", "relation": "method", "confidence": "EXTRACTED", "source_file": "A:\\Unversidad\\_PRACTICAS_UNI\\CODIGO\\SOEA\\src\\SOEA.Engine.ConstraintProg\\MotorConstraintProgramming.cs", "source_location": "L36", "weight": 1.0}, {"source": "soea_engine_constraintprog_motorconstraintprogramming_motorconstraintprogramming_resolverfactibilidadasync", "target": "ienumerable", "relation": "references", "confidence": "EXTRACTED", "source_file": "A:\\Unversidad\\_PRACTICAS_UNI\\CODIGO\\SOEA\\src\\SOEA.Engine.ConstraintProg\\MotorConstraintProgramming.cs", "source_location": "L36", "weight": 1.0, "context": "parameter_type"}, {"source": "soea_engine_constraintprog_motorconstraintprogramming_motorconstraintprogramming_resolverfactibilidadasync", "target": "sesion", "relation": "references", "confidence": "EXTRACTED", "source_file": "A:\\Unversidad\\_PRACTICAS_UNI\\CODIGO\\SOEA\\src\\SOEA.Engine.ConstraintProg\\MotorConstraintProgramming.cs", "source_location": "L36", "weight": 1.0, "context": "generic_arg"}, {"source": "soea_engine_constraintprog_motorconstraintprogramming_motorconstraintprogramming_resolverfactibilidadasync", "target": "ienumerable", "relation": "references", "confidence": "EXTRACTED", "source_file": "A:\\Unversidad\\_PRACTICAS_UNI\\CODIGO\\SOEA\\src\\SOEA.Engine.ConstraintProg\\MotorConstraintProgramming.cs", "source_location": "L36", "weight": 1.0, "context": "parameter_type"}, {"source": "soea_engine_constraintprog_motorconstraintprogramming_motorconstraintprogramming_resolverfactibilidadasync", "target": "bloquetiempo", "relation": "references", "confidence": "EXTRACTED", "source_file": "A:\\Unversidad\\_PRACTICAS_UNI\\CODIGO\\SOEA\\src\\SOEA.Engine.ConstraintProg\\MotorConstraintProgramming.cs", "source_location": "L36", "weight": 1.0, "context": "generic_arg"}, {"source": "soea_engine_constraintprog_motorconstraintprogramming_motorconstraintprogramming_resolverfactibilidadasync", "target": "ienumerable", "relation": "references", "confidence": "EXTRACTED", "source_file": "A:\\Unversidad\\_PRACTICAS_UNI\\CODIGO\\SOEA\\src\\SOEA.Engine.ConstraintProg\\MotorConstraintProgramming.cs", "source_location": "L36", "weight": 1.0, "context": "parameter_type"}, {"source": "soea_engine_constraintprog_motorconstraintprogramming_motorconstraintprogramming_resolverfactibilidadasync", "target": "espacio", "relation": "references", "confidence": "EXTRACTED", "source_file": "A:\\Unversidad\\_PRACTICAS_UNI\\CODIGO\\SOEA\\src\\SOEA.Engine.ConstraintProg\\MotorConstraintProgramming.cs", "source_location": "L36", "weight": 1.0, "context": "generic_arg"}, {"source": "soea_engine_constraintprog_motorconstraintprogramming_motorconstraintprogramming_resolverfactibilidadasync", "target": "ienumerable", "relation": "references", "confidence": "EXTRACTED", "source_file": "A:\\Unversidad\\_PRACTICAS_UNI\\CODIGO\\SOEA\\src\\SOEA.Engine.ConstraintProg\\MotorConstraintProgramming.cs", "source_location": "L36", "weight": 1.0, "context": "parameter_type"}, {"source": "soea_engine_constraintprog_motorconstraintprogramming_motorconstraintprogramming_resolverfactibilidadasync", "target": "docente", "relation": "references", "confidence": "EXTRACTED", "source_file": "A:\\Unversidad\\_PRACTICAS_UNI\\CODIGO\\SOEA\\src\\SOEA.Engine.ConstraintProg\\MotorConstraintProgramming.cs", "source_location": "L36", "weight": 1.0, "context": "generic_arg"}, {"source": "soea_engine_constraintprog_motorconstraintprogramming_motorconstraintprogramming_resolverfactibilidadasync", "target": "task", "relation": "references", "confidence": "EXTRACTED", "source_file": "A:\\Unversidad\\_PRACTICAS_UNI\\CODIGO\\SOEA\\src\\SOEA.Engine.ConstraintProg\\MotorConstraintProgramming.cs", "source_location": "L36", "weight": 1.0, "context": "return_type"}, {"source": "soea_engine_constraintprog_motorconstraintprogramming_motorconstraintprogramming_resolverfactibilidadasync", "target": "resultadofactibilidad", "relation": "references", "confidence": "EXTRACTED", "source_file": "A:\\Unversidad\\_PRACTICAS_UNI\\CODIGO\\SOEA\\src\\SOEA.Engine.ConstraintProg\\MotorConstraintProgramming.cs", "source_location": "L36", "weight": 1.0, "context": "generic_arg"}, {"source": "soea_engine_constraintprog_motorconstraintprogramming_motorconstraintprogramming", "target": "soea_engine_constraintprog_motorconstraintprogramming_motorconstraintprogramming_modalidadde", "relation": "method", "confidence": "EXTRACTED", "source_file": "A:\\Unversidad\\_PRACTICAS_UNI\\CODIGO\\SOEA\\src\\SOEA.Engine.ConstraintProg\\MotorConstraintProgramming.cs", "source_location": "L51", "weight": 1.0}, {"source": "soea_engine_constraintprog_motorconstraintprogramming_motorconstraintprogramming_modalidadde", "target": "sesion", "relation": "references", "confidence": "EXTRACTED", "source_file": "A:\\Unversidad\\_PRACTICAS_UNI\\CODIGO\\SOEA\\src\\SOEA.Engine.ConstraintProg\\MotorConstraintProgramming.cs", "source_location": "L51", "weight": 1.0, "context": "parameter_type"}, {"source": "soea_engine_constraintprog_motorconstraintprogramming_motorconstraintprogramming_modalidadde", "target": "semanaacademica", "relation": "references", "confidence": "EXTRACTED", "source_file": "A:\\Unversidad\\_PRACTICAS_UNI\\CODIGO\\SOEA\\src\\SOEA.Engine.ConstraintProg\\MotorConstraintProgramming.cs", "source_location": "L51", "weight": 1.0, "context": "parameter_type"}, {"source": "soea_engine_constraintprog_motorconstraintprogramming_motorconstraintprogramming_modalidadde", "target": "modalidad", "relation": "references", "confidence": "EXTRACTED", "source_file": "A:\\Unversidad\\_PRACTICAS_UNI\\CODIGO\\SOEA\\src\\SOEA.Engine.ConstraintProg\\MotorConstraintProgramming.cs", "source_location": "L51", "weight": 1.0, "context": "return_type"}, {"source": "soea_engine_constraintprog_motorconstraintprogramming_motorconstraintprogramming", "target": "soea_engine_constraintprog_motorconstraintprogramming_motorconstraintprogramming_resolversincrono", "relation": "method", "confidence": "EXTRACTED", "source_file": "A:\\Unversidad\\_PRACTICAS_UNI\\CODIGO\\SOEA\\src\\SOEA.Engine.ConstraintProg\\MotorConstraintProgramming.cs", "source_location": "L66", "weight": 1.0}, {"source": "soea_engine_constraintprog_motorconstraintprogramming_motorconstraintprogramming_resolversincrono", "target": "list", "relation": "references", "confidence": "EXTRACTED", "source_file": "A:\\Unversidad\\_PRACTICAS_UNI\\CODIGO\\SOEA\\src\\SOEA.Engine.ConstraintProg\\MotorConstraintProgramming.cs", "source_location": "L66", "weight": 1.0, "context": "parameter_type"}, {"source": "soea_engine_constraintprog_motorconstraintprogramming_motorconstraintprogramming_resolversincrono", "target": "sesion", "relation": "references", "confidence": "EXTRACTED", "source_file": "A:\\Unversidad\\_PRACTICAS_UNI\\CODIGO\\SOEA\\src\\SOEA.Engine.ConstraintProg\\MotorConstraintProgramming.cs", "source_location": "L66", "weight": 1.0, "context": "generic_arg"}, {"source": "soea_engine_constraintprog_motorconstraintprogramming_motorconstraintprogramming_resolversincrono", "target": "list", "relation": "references", "confidence": "EXTRACTED", "source_file": "A:\\Unversidad\\_PRACTICAS_UNI\\CODIGO\\SOEA\\src\\SOEA.Engine.ConstraintProg\\MotorConstraintProgramming.cs", "source_location": "L66", "weight": 1.0, "context": "parameter_type"}, {"source": "soea_engine_constraintprog_motorconstraintprogramming_motorconstraintprogramming_resolversincrono", "target": "bloquetiempo", "relation": "references", "confidence": "EXTRACTED", "source_file": "A:\\Unversidad\\_PRACTICAS_UNI\\CODIGO\\SOEA\\src\\SOEA.Engine.ConstraintProg\\MotorConstraintProgramming.cs", "source_location": "L66", "weight": 1.0, "context": "generic_arg"}, {"source": "soea_engine_constraintprog_motorconstraintprogramming_motorconstraintprogramming_resolversincrono", "target": "list", "relation": "references", "confidence": "EXTRACTED", "source_file": "A:\\Unversidad\\_PRACTICAS_UNI\\CODIGO\\SOEA\\src\\SOEA.Engine.ConstraintProg\\MotorConstraintProgramming.cs", "source_location": "L66", "weight": 1.0, "context": "parameter_type"}, {"source": "soea_engine_constraintprog_motorconstraintprogramming_motorconstraintprogramming_resolversincrono", "target": "espacio", "relation": "references", "confidence": "EXTRACTED", "source_file": "A:\\Unversidad\\_PRACTICAS_UNI\\CODIGO\\SOEA\\src\\SOEA.Engine.ConstraintProg\\MotorConstraintProgramming.cs", "source_location": "L66", "weight": 1.0, "context": "generic_arg"}, {"source": "soea_engine_constraintprog_motorconstraintprogramming_motorconstraintprogramming_resolversincrono", "target": "list", "relation": "references", "confidence": "EXTRACTED", "source_file": "A:\\Unversidad\\_PRACTICAS_UNI\\CODIGO\\SOEA\\src\\SOEA.Engine.ConstraintProg\\MotorConstraintProgramming.cs", "source_location": "L66", "weight": 1.0, "context": "parameter_type"}, {"source": "soea_engine_constraintprog_motorconstraintprogramming_motorconstraintprogramming_resolversincrono", "target": "docente", "relation": "references", "confidence": "EXTRACTED", "source_file": "A:\\Unversidad\\_PRACTICAS_UNI\\CODIGO\\SOEA\\src\\SOEA.Engine.ConstraintProg\\MotorConstraintProgramming.cs", "source_location": "L66", "weight": 1.0, "context": "generic_arg"}, {"source": "soea_engine_constraintprog_motorconstraintprogramming_motorconstraintprogramming_resolversincrono", "target": "resultadofactibilidad", "relation": "references", "confidence": "EXTRACTED", "source_file": "A:\\Unversidad\\_PRACTICAS_UNI\\CODIGO\\SOEA\\src\\SOEA.Engine.ConstraintProg\\MotorConstraintProgramming.cs", "source_location": "L66", "weight": 1.0, "context": "return_type"}, {"source": "soea_engine_constraintprog_motorconstraintprogramming_motorconstraintprogramming_resolverfactibilidadasync", "target": "soea_engine_constraintprog_motorconstraintprogramming_motorconstraintprogramming_resolversincrono", "relation": "calls", "context": "call", "confidence": "EXTRACTED", "source_file": "A:\\Unversidad\\_PRACTICAS_UNI\\CODIGO\\SOEA\\src\\SOEA.Engine.ConstraintProg\\MotorConstraintProgramming.cs", "source_location": "L42", "weight": 1.0}, {"source": "soea_engine_constraintprog_motorconstraintprogramming_motorconstraintprogramming_resolversincrono", "target": "soea_engine_constraintprog_motorconstraintprogramming_motorconstraintprogramming_modalidadde", "relation": "calls", "context": "call", "confidence": "EXTRACTED", "source_file": "A:\\Unversidad\\_PRACTICAS_UNI\\CODIGO\\SOEA\\src\\SOEA.Engine.ConstraintProg\\MotorConstraintProgramming.cs", "source_location": "L83", "weight": 1.0}], "raw_calls": [{"caller_nid": "soea_engine_constraintprog_motorconstraintprogramming_motorconstraintprogramming_resolverfactibilidadasync", "callee": "ToList", "is_member_call": true, "source_file": "A:\\Unversidad\\_PRACTICAS_UNI\\CODIGO\\SOEA\\src\\SOEA.Engine.ConstraintProg\\MotorConstraintProgramming.cs", "source_location": "L42"}, {"caller_nid": "soea_engine_constraintprog_motorconstraintprogramming_motorconstraintprogramming_resolverfactibilidadasync", "callee": "ToList", "is_member_call": true, "source_file": "A:\\Unversidad\\_PRACTICAS_UNI\\CODIGO\\SOEA\\src\\SOEA.Engine.ConstraintProg\\MotorConstraintProgramming.cs", "source_location": "L42"}, {"caller_nid": "soea_engine_constraintprog_motorconstraintprogramming_motorconstraintprogramming_resolverfactibilidadasync", "callee": "ToList", "is_member_call": true, "source_file": "A:\\Unversidad\\_PRACTICAS_UNI\\CODIGO\\SOEA\\src\\SOEA.Engine.ConstraintProg\\MotorConstraintProgramming.cs", "source_location": "L42"}, {"caller_nid": "soea_engine_constraintprog_motorconstraintprogramming_motorconstraintprogramming_resolverfactibilidadasync", "callee": "ToList", "is_member_call": true, "source_file": "A:\\Unversidad\\_PRACTICAS_UNI\\CODIGO\\SOEA\\src\\SOEA.Engine.ConstraintProg\\MotorConstraintProgramming.cs", "source_location": "L42"}, {"caller_nid": "soea_engine_constraintprog_motorconstraintprogramming_motorconstraintprogramming_resolverfactibilidadasync", "callee": "FromResult", "is_member_call": true, "source_file": "A:\\Unversidad\\_PRACTICAS_UNI\\CODIGO\\SOEA\\src\\SOEA.Engine.ConstraintProg\\MotorConstraintProgramming.cs", "source_location": "L43"}, {"caller_nid": "soea_engine_constraintprog_motorconstraintprogramming_motorconstraintprogramming_resolversincrono", "callee": "Any", "is_member_call": true, "source_file": "A:\\Unversidad\\_PRACTICAS_UNI\\CODIGO\\SOEA\\src\\SOEA.Engine.ConstraintProg\\MotorConstraintProgramming.cs", "source_location": "L72"}, {"caller_nid": "soea_engine_constraintprog_motorconstraintprogramming_motorconstraintprogramming_resolversincrono", "callee": "Any", "is_member_call": true, "source_file": "A:\\Unversidad\\_PRACTICAS_UNI\\CODIGO\\SOEA\\src\\SOEA.Engine.ConstraintProg\\MotorConstraintProgramming.cs", "source_location": "L72"}, {"caller_nid": "soea_engine_constraintprog_motorconstraintprogramming_motorconstraintprogramming_resolversincrono", "callee": "LogWarning", "is_member_call": true, "source_file": "A:\\Unversidad\\_PRACTICAS_UNI\\CODIGO\\SOEA\\src\\SOEA.Engine.ConstraintProg\\MotorConstraintProgramming.cs", "source_location": "L74"}, {"caller_nid": "soea_engine_constraintprog_motorconstraintprogramming_motorconstraintprogramming_resolversincrono", "callee": "Sum", "is_member_call": true, "source_file": "A:\\Unversidad\\_PRACTICAS_UNI\\CODIGO\\SOEA\\src\\SOEA.Engine.ConstraintProg\\MotorConstraintProgramming.cs", "source_location": "L82"}, {"caller_nid": "soea_engine_constraintprog_motorconstraintprogramming_motorconstraintprogramming_resolversincrono", "callee": "Where", "is_member_call": true, "source_file": "A:\\Unversidad\\_PRACTICAS_UNI\\CODIGO\\SOEA\\src\\SOEA.Engine.ConstraintProg\\MotorConstraintProgramming.cs", "source_location": "L82"}, {"caller_nid": "soea_engine_constraintprog_motorconstraintprogramming_motorconstraintprogramming_resolversincrono", "callee": "LogInformation", "is_member_call": true, "source_file": "A:\\Unversidad\\_PRACTICAS_UNI\\CODIGO\\SOEA\\src\\SOEA.Engine.ConstraintProg\\MotorConstraintProgramming.cs", "source_location": "L86"}, {"caller_nid": "soea_engine_constraintprog_motorconstraintprogramming_motorconstraintprogramming_resolversincrono", "callee": "LogError", "is_member_call": true, "source_file": "A:\\Unversidad\\_PRACTICAS_UNI\\CODIGO\\SOEA\\src\\SOEA.Engine.ConstraintProg\\MotorConstraintProgramming.cs", "source_location": "L95"}, {"caller_nid": "soea_engine_constraintprog_motorconstraintprogramming_motorconstraintprogramming_resolversincrono", "callee": "ToDictionary", "is_member_call": true, "source_file": "A:\\Unversidad\\_PRACTICAS_UNI\\CODIGO\\SOEA\\src\\SOEA.Engine.ConstraintProg\\MotorConstraintProgramming.cs", "source_location": "L109"}, {"caller_nid": "soea_engine_constraintprog_motorconstraintprogramming_motorconstraintprogramming_resolversincrono", "callee": "RangosPorDia", "is_member_call": true, "source_file": "A:\\Unversidad\\_PRACTICAS_UNI\\CODIGO\\SOEA\\src\\SOEA.Engine.ConstraintProg\\MotorConstraintProgramming.cs", "source_location": "L110"}, {"caller_nid": "soea_engine_constraintprog_motorconstraintprogramming_motorconstraintprogramming_resolversincrono", "callee": "DiaPorBloqueIdx", "is_member_call": true, "source_file": "A:\\Unversidad\\_PRACTICAS_UNI\\CODIGO\\SOEA\\src\\SOEA.Engine.ConstraintProg\\MotorConstraintProgramming.cs", "source_location": "L111"}, {"caller_nid": "soea_engine_constraintprog_motorconstraintprogramming_motorconstraintprogramming_resolversincrono", "callee": "Max", "is_member_call": true, "source_file": "A:\\Unversidad\\_PRACTICAS_UNI\\CODIGO\\SOEA\\src\\SOEA.Engine.ConstraintProg\\MotorConstraintProgramming.cs", "source_location": "L122"}, {"caller_nid": "soea_engine_constraintprog_motorconstraintprogramming_motorconstraintprogramming_resolversincrono", "callee": "Ceiling", "is_member_call": true, "source_file": "A:\\Unversidad\\_PRACTICAS_UNI\\CODIGO\\SOEA\\src\\SOEA.Engine.ConstraintProg\\MotorConstraintProgramming.cs", "source_location": "L122"}, {"caller_nid": "soea_engine_constraintprog_motorconstraintprogramming_motorconstraintprogramming_resolversincrono", "callee": "NewIntVar", "is_member_call": true, "source_file": "A:\\Unversidad\\_PRACTICAS_UNI\\CODIGO\\SOEA\\src\\SOEA.Engine.ConstraintProg\\MotorConstraintProgramming.cs", "source_location": "L128"}, {"caller_nid": "soea_engine_constraintprog_motorconstraintprogramming_motorconstraintprogramming_resolversincrono", "callee": "NewIntVar", "is_member_call": true, "source_file": "A:\\Unversidad\\_PRACTICAS_UNI\\CODIGO\\SOEA\\src\\SOEA.Engine.ConstraintProg\\MotorConstraintProgramming.cs", "source_location": "L129"}, {"caller_nid": "soea_engine_constraintprog_motorconstraintprogramming_motorconstraintprogramming_resolversincrono", "callee": "NewIntervalVar", "is_member_call": true, "source_file": "A:\\Unversidad\\_PRACTICAS_UNI\\CODIGO\\SOEA\\src\\SOEA.Engine.ConstraintProg\\MotorConstraintProgramming.cs", "source_location": "L132"}, {"caller_nid": "soea_engine_constraintprog_motorconstraintprogramming_motorconstraintprogramming_resolversincrono", "callee": "Any", "is_member_call": true, "source_file": "A:\\Unversidad\\_PRACTICAS_UNI\\CODIGO\\SOEA\\src\\SOEA.Engine.ConstraintProg\\MotorConstraintProgramming.cs", "source_location": "L134"}, {"caller_nid": "soea_engine_constraintprog_motorconstraintprogramming_motorconstraintprogramming_resolversincrono", "callee": "NewIntVar", "is_member_call": true, "source_file": "A:\\Unversidad\\_PRACTICAS_UNI\\CODIGO\\SOEA\\src\\SOEA.Engine.ConstraintProg\\MotorConstraintProgramming.cs", "source_location": "L135"}, {"caller_nid": "soea_engine_constraintprog_motorconstraintprogramming_motorconstraintprogramming_resolversincrono", "callee": "Add", "is_member_call": true, "source_file": "A:\\Unversidad\\_PRACTICAS_UNI\\CODIGO\\SOEA\\src\\SOEA.Engine.ConstraintProg\\MotorConstraintProgramming.cs", "source_location": "L143"}, {"caller_nid": "soea_engine_constraintprog_motorconstraintprogramming_motorconstraintprogramming_resolversincrono", "callee": "TryGetValue", "is_member_call": true, "source_file": "A:\\Unversidad\\_PRACTICAS_UNI\\CODIGO\\SOEA\\src\\SOEA.Engine.ConstraintProg\\MotorConstraintProgramming.cs", "source_location": "L150"}, {"caller_nid": "soea_engine_constraintprog_motorconstraintprogramming_motorconstraintprogramming_resolversincrono", "callee": "CabeEnDia", "is_member_call": true, "source_file": "A:\\Unversidad\\_PRACTICAS_UNI\\CODIGO\\SOEA\\src\\SOEA.Engine.ConstraintProg\\MotorConstraintProgramming.cs", "source_location": "L153"}, {"caller_nid": "soea_engine_constraintprog_motorconstraintprogramming_motorconstraintprogramming_resolversincrono", "callee": "AddHint", "is_member_call": true, "source_file": "A:\\Unversidad\\_PRACTICAS_UNI\\CODIGO\\SOEA\\src\\SOEA.Engine.ConstraintProg\\MotorConstraintProgramming.cs", "source_location": "L156"}, {"caller_nid": "soea_engine_constraintprog_motorconstraintprogramming_motorconstraintprogramming_resolversincrono", "callee": "TryGetValue", "is_member_call": true, "source_file": "A:\\Unversidad\\_PRACTICAS_UNI\\CODIGO\\SOEA\\src\\SOEA.Engine.ConstraintProg\\MotorConstraintProgramming.cs", "source_location": "L167"}, {"caller_nid": "soea_engine_constraintprog_motorconstraintprogramming_motorconstraintprogramming_resolversincrono", "callee": "ToHashSet", "is_member_call": true, "source_file": "A:\\Unversidad\\_PRACTICAS_UNI\\CODIGO\\SOEA\\src\\SOEA.Engine.ConstraintProg\\MotorConstraintProgramming.cs", "source_location": "L169"}, {"caller_nid": "soea_engine_constraintprog_motorconstraintprogramming_motorconstraintprogramming_resolversincrono", "callee": "Select", "is_member_call": true, "source_file": "A:\\Unversidad\\_PRACTICAS_UNI\\CODIGO\\SOEA\\src\\SOEA.Engine.ConstraintProg\\MotorConstraintProgramming.cs", "source_location": "L169"}, {"caller_nid": "soea_engine_constraintprog_motorconstraintprogramming_motorconstraintprogramming_resolversincrono", "callee": "Where", "is_member_call": true, "source_file": "A:\\Unversidad\\_PRACTICAS_UNI\\CODIGO\\SOEA\\src\\SOEA.Engine.ConstraintProg\\MotorConstraintProgramming.cs", "source_location": "L169"}, {"caller_nid": "soea_engine_constraintprog_motorconstraintprogramming_motorconstraintprogramming_resolversincrono", "callee": "ContainsKey", "is_member_call": true, "source_file": "A:\\Unversidad\\_PRACTICAS_UNI\\CODIGO\\SOEA\\src\\SOEA.Engine.ConstraintProg\\MotorConstraintProgramming.cs", "source_location": "L170"}, {"caller_nid": "soea_engine_constraintprog_motorconstraintprogramming_motorconstraintprogramming_resolversincrono", "callee": "LogWarning", "is_member_call": true, "source_file": "A:\\Unversidad\\_PRACTICAS_UNI\\CODIGO\\SOEA\\src\\SOEA.Engine.ConstraintProg\\MotorConstraintProgramming.cs", "source_location": "L176"}, {"caller_nid": "soea_engine_constraintprog_motorconstraintprogramming_motorconstraintprogramming_resolversincrono", "callee": "ToArray", "is_member_call": true, "source_file": "A:\\Unversidad\\_PRACTICAS_UNI\\CODIGO\\SOEA\\src\\SOEA.Engine.ConstraintProg\\MotorConstraintProgramming.cs", "source_location": "L183"}, {"caller_nid": "soea_engine_constraintprog_motorconstraintprogramming_motorconstraintprogramming_resolversincrono", "callee": "Select", "is_member_call": true, "source_file": "A:\\Unversidad\\_PRACTICAS_UNI\\CODIGO\\SOEA\\src\\SOEA.Engine.ConstraintProg\\MotorConstraintProgramming.cs", "source_location": "L183"}, {"caller_nid": "soea_engine_constraintprog_motorconstraintprogramming_motorconstraintprogramming_resolversincrono", "callee": "StartsValidos", "is_member_call": true, "source_file": "A:\\Unversidad\\_PRACTICAS_UNI\\CODIGO\\SOEA\\src\\SOEA.Engine.ConstraintProg\\MotorConstraintProgramming.cs", "source_location": "L183"}, {"caller_nid": "soea_engine_constraintprog_motorconstraintprogramming_motorconstraintprogramming_resolversincrono", "callee": "TryGetValue", "is_member_call": true, "source_file": "A:\\Unversidad\\_PRACTICAS_UNI\\CODIGO\\SOEA\\src\\SOEA.Engine.ConstraintProg\\MotorConstraintProgramming.cs", "source_location": "L190"}, {"caller_nid": "soea_engine_constraintprog_motorconstraintprogramming_motorconstraintprogramming_resolversincrono", "callee": "ToString", "is_member_call": true, "source_file": "A:\\Unversidad\\_PRACTICAS_UNI\\CODIGO\\SOEA\\src\\SOEA.Engine.ConstraintProg\\MotorConstraintProgramming.cs", "source_location": "L190"}, {"caller_nid": "soea_engine_constraintprog_motorconstraintprogramming_motorconstraintprogramming_resolversincrono", "callee": "LogError", "is_member_call": true, "source_file": "A:\\Unversidad\\_PRACTICAS_UNI\\CODIGO\\SOEA\\src\\SOEA.Engine.ConstraintProg\\MotorConstraintProgramming.cs", "source_location": "L192"}, {"caller_nid": "soea_engine_constraintprog_motorconstraintprogramming_motorconstraintprogramming_resolversincrono", "callee": "FromValues", "is_member_call": true, "source_file": "A:\\Unversidad\\_PRACTICAS_UNI\\CODIGO\\SOEA\\src\\SOEA.Engine.ConstraintProg\\MotorConstraintProgramming.cs", "source_location": "L196"}, {"caller_nid": "soea_engine_constraintprog_motorconstraintprogramming_motorconstraintprogramming_resolversincrono", "callee": "AddLinearExpressionInDomain", "is_member_call": true, "source_file": "A:\\Unversidad\\_PRACTICAS_UNI\\CODIGO\\SOEA\\src\\SOEA.Engine.ConstraintProg\\MotorConstraintProgramming.cs", "source_location": "L198"}, {"caller_nid": "soea_engine_constraintprog_motorconstraintprogramming_motorconstraintprogramming_resolversincrono", "callee": "ToList", "is_member_call": true, "source_file": "A:\\Unversidad\\_PRACTICAS_UNI\\CODIGO\\SOEA\\src\\SOEA.Engine.ConstraintProg\\MotorConstraintProgramming.cs", "source_location": "L204"}, {"caller_nid": "soea_engine_constraintprog_motorconstraintprogramming_motorconstraintprogramming_resolversincrono", "callee": "Where", "is_member_call": true, "source_file": "A:\\Unversidad\\_PRACTICAS_UNI\\CODIGO\\SOEA\\src\\SOEA.Engine.ConstraintProg\\MotorConstraintProgramming.cs", "source_location": "L204"}, {"caller_nid": "soea_engine_constraintprog_motorconstraintprogramming_motorconstraintprogramming_resolversincrono", "callee": "GroupBy", "is_member_call": true, "source_file": "A:\\Unversidad\\_PRACTICAS_UNI\\CODIGO\\SOEA\\src\\SOEA.Engine.ConstraintProg\\MotorConstraintProgramming.cs", "source_location": "L204"}, {"caller_nid": "soea_engine_constraintprog_motorconstraintprogramming_motorconstraintprogramming_resolversincrono", "callee": "TryGetValue", "is_member_call": true, "source_file": "A:\\Unversidad\\_PRACTICAS_UNI\\CODIGO\\SOEA\\src\\SOEA.Engine.ConstraintProg\\MotorConstraintProgramming.cs", "source_location": "L207"}, {"caller_nid": "soea_engine_constraintprog_motorconstraintprogramming_motorconstraintprogramming_resolversincrono", "callee": "LogWarning", "is_member_call": true, "source_file": "A:\\Unversidad\\_PRACTICAS_UNI\\CODIGO\\SOEA\\src\\SOEA.Engine.ConstraintProg\\MotorConstraintProgramming.cs", "source_location": "L211"}, {"caller_nid": "soea_engine_constraintprog_motorconstraintprogramming_motorconstraintprogramming_resolversincrono", "callee": "Sum", "is_member_call": true, "source_file": "A:\\Unversidad\\_PRACTICAS_UNI\\CODIGO\\SOEA\\src\\SOEA.Engine.ConstraintProg\\MotorConstraintProgramming.cs", "source_location": "L217"}, {"caller_nid": "soea_engine_constraintprog_motorconstraintprogramming_motorconstraintprogramming_resolversincrono", "callee": "LogError", "is_member_call": true, "source_file": "A:\\Unversidad\\_PRACTICAS_UNI\\CODIGO\\SOEA\\src\\SOEA.Engine.ConstraintProg\\MotorConstraintProgramming.cs", "source_location": "L221"}, {"caller_nid": "soea_engine_constraintprog_motorconstraintprogramming_motorconstraintprogramming_resolversincrono", "callee": "Count", "is_member_call": true, "source_file": "A:\\Unversidad\\_PRACTICAS_UNI\\CODIGO\\SOEA\\src\\SOEA.Engine.ConstraintProg\\MotorConstraintProgramming.cs", "source_location": "L225"}, {"caller_nid": "soea_engine_constraintprog_motorconstraintprogramming_motorconstraintprogramming_resolversincrono", "callee": "ContainsKey", "is_member_call": true, "source_file": "A:\\Unversidad\\_PRACTICAS_UNI\\CODIGO\\SOEA\\src\\SOEA.Engine.ConstraintProg\\MotorConstraintProgramming.cs", "source_location": "L225"}, {"caller_nid": "soea_engine_constraintprog_motorconstraintprogramming_motorconstraintprogramming_resolversincrono", "callee": "LogError", "is_member_call": true, "source_file": "A:\\Unversidad\\_PRACTICAS_UNI\\CODIGO\\SOEA\\src\\SOEA.Engine.ConstraintProg\\MotorConstraintProgramming.cs", "source_location": "L229"}, {"caller_nid": "soea_engine_constraintprog_motorconstraintprogramming_motorconstraintprogramming_resolversincrono", "callee": "ToArray", "is_member_call": true, "source_file": "A:\\Unversidad\\_PRACTICAS_UNI\\CODIGO\\SOEA\\src\\SOEA.Engine.ConstraintProg\\MotorConstraintProgramming.cs", "source_location": "L240"}, {"caller_nid": "soea_engine_constraintprog_motorconstraintprogramming_motorconstraintprogramming_resolversincrono", "callee": "Select", "is_member_call": true, "source_file": "A:\\Unversidad\\_PRACTICAS_UNI\\CODIGO\\SOEA\\src\\SOEA.Engine.ConstraintProg\\MotorConstraintProgramming.cs", "source_location": "L240"}, {"caller_nid": "soea_engine_constraintprog_motorconstraintprogramming_motorconstraintprogramming_resolversincrono", "callee": "AddNoOverlap", "is_member_call": true, "source_file": "A:\\Unversidad\\_PRACTICAS_UNI\\CODIGO\\SOEA\\src\\SOEA.Engine.ConstraintProg\\MotorConstraintProgramming.cs", "source_location": "L242"}, {"caller_nid": "soea_engine_constraintprog_motorconstraintprogramming_motorconstraintprogramming_resolversincrono", "callee": "Any", "is_member_call": true, "source_file": "A:\\Unversidad\\_PRACTICAS_UNI\\CODIGO\\SOEA\\src\\SOEA.Engine.ConstraintProg\\MotorConstraintProgramming.cs", "source_location": "L247"}, {"caller_nid": "soea_engine_constraintprog_motorconstraintprogramming_motorconstraintprogramming_resolversincrono", "callee": "Any", "is_member_call": true, "source_file": "A:\\Unversidad\\_PRACTICAS_UNI\\CODIGO\\SOEA\\src\\SOEA.Engine.ConstraintProg\\MotorConstraintProgramming.cs", "source_location": "L247"}, {"caller_nid": "soea_engine_constraintprog_motorconstraintprogramming_motorconstraintprogramming_resolversincrono", "callee": "Any", "is_member_call": true, "source_file": "A:\\Unversidad\\_PRACTICAS_UNI\\CODIGO\\SOEA\\src\\SOEA.Engine.ConstraintProg\\MotorConstraintProgramming.cs", "source_location": "L253"}, {"caller_nid": "soea_engine_constraintprog_motorconstraintprogramming_motorconstraintprogramming_resolversincrono", "callee": "ContainsKey", "is_member_call": true, "source_file": "A:\\Unversidad\\_PRACTICAS_UNI\\CODIGO\\SOEA\\src\\SOEA.Engine.ConstraintProg\\MotorConstraintProgramming.cs", "source_location": "L253"}, {"caller_nid": "soea_engine_constraintprog_motorconstraintprogramming_motorconstraintprogramming_resolversincrono", "callee": "FirstOrDefault", "is_member_call": true, "source_file": "A:\\Unversidad\\_PRACTICAS_UNI\\CODIGO\\SOEA\\src\\SOEA.Engine.ConstraintProg\\MotorConstraintProgramming.cs", "source_location": "L259"}, {"caller_nid": "soea_engine_constraintprog_motorconstraintprogramming_motorconstraintprogramming_resolversincrono", "callee": "Add", "is_member_call": true, "source_file": "A:\\Unversidad\\_PRACTICAS_UNI\\CODIGO\\SOEA\\src\\SOEA.Engine.ConstraintProg\\MotorConstraintProgramming.cs", "source_location": "L268"}, {"caller_nid": "soea_engine_constraintprog_motorconstraintprogramming_motorconstraintprogramming_resolversincrono", "callee": "LogError", "is_member_call": true, "source_file": "A:\\Unversidad\\_PRACTICAS_UNI\\CODIGO\\SOEA\\src\\SOEA.Engine.ConstraintProg\\MotorConstraintProgramming.cs", "source_location": "L274"}, {"caller_nid": "soea_engine_constraintprog_motorconstraintprogramming_motorconstraintprogramming_resolversincrono", "callee": "TryGetValue", "is_member_call": true, "source_file": "A:\\Unversidad\\_PRACTICAS_UNI\\CODIGO\\SOEA\\src\\SOEA.Engine.ConstraintProg\\MotorConstraintProgramming.cs", "source_location": "L289"}, {"caller_nid": "soea_engine_constraintprog_motorconstraintprogramming_motorconstraintprogramming_resolversincrono", "callee": "NewBoolVar", "is_member_call": true, "source_file": "A:\\Unversidad\\_PRACTICAS_UNI\\CODIGO\\SOEA\\src\\SOEA.Engine.ConstraintProg\\MotorConstraintProgramming.cs", "source_location": "L294"}, {"caller_nid": "soea_engine_constraintprog_motorconstraintprogramming_motorconstraintprogramming_resolversincrono", "callee": "Add", "is_member_call": true, "source_file": "A:\\Unversidad\\_PRACTICAS_UNI\\CODIGO\\SOEA\\src\\SOEA.Engine.ConstraintProg\\MotorConstraintProgramming.cs", "source_location": "L295"}, {"caller_nid": "soea_engine_constraintprog_motorconstraintprogramming_motorconstraintprogramming_resolversincrono", "callee": "OnlyEnforceIf", "is_member_call": true, "source_file": "A:\\Unversidad\\_PRACTICAS_UNI\\CODIGO\\SOEA\\src\\SOEA.Engine.ConstraintProg\\MotorConstraintProgramming.cs", "source_location": "L297"}, {"caller_nid": "soea_engine_constraintprog_motorconstraintprogramming_motorconstraintprogramming_resolversincrono", "callee": "Add", "is_member_call": true, "source_file": "A:\\Unversidad\\_PRACTICAS_UNI\\CODIGO\\SOEA\\src\\SOEA.Engine.ConstraintProg\\MotorConstraintProgramming.cs", "source_location": "L297"}, {"caller_nid": "soea_engine_constraintprog_motorconstraintprogramming_motorconstraintprogramming_resolversincrono", "callee": "NewOptionalIntervalVar", "is_member_call": true, "source_file": "A:\\Unversidad\\_PRACTICAS_UNI\\CODIGO\\SOEA\\src\\SOEA.Engine.ConstraintProg\\MotorConstraintProgramming.cs", "source_location": "L299"}, {"caller_nid": "soea_engine_constraintprog_motorconstraintprogramming_motorconstraintprogramming_resolversincrono", "callee": "Add", "is_member_call": true, "source_file": "A:\\Unversidad\\_PRACTICAS_UNI\\CODIGO\\SOEA\\src\\SOEA.Engine.ConstraintProg\\MotorConstraintProgramming.cs", "source_location": "L305"}, {"caller_nid": "soea_engine_constraintprog_motorconstraintprogramming_motorconstraintprogramming_resolversincrono", "callee": "AddExactlyOne", "is_member_call": true, "source_file": "A:\\Unversidad\\_PRACTICAS_UNI\\CODIGO\\SOEA\\src\\SOEA.Engine.ConstraintProg\\MotorConstraintProgramming.cs", "source_location": "L308"}, {"caller_nid": "soea_engine_constraintprog_motorconstraintprogramming_motorconstraintprogramming_resolversincrono", "callee": "AddNoOverlap", "is_member_call": true, "source_file": "A:\\Unversidad\\_PRACTICAS_UNI\\CODIGO\\SOEA\\src\\SOEA.Engine.ConstraintProg\\MotorConstraintProgramming.cs", "source_location": "L315"}, {"caller_nid": "soea_engine_constraintprog_motorconstraintprogramming_motorconstraintprogramming_resolversincrono", "callee": "WriteAllText", "is_member_call": true, "source_file": "A:\\Unversidad\\_PRACTICAS_UNI\\CODIGO\\SOEA\\src\\SOEA.Engine.ConstraintProg\\MotorConstraintProgramming.cs", "source_location": "L322"}, {"caller_nid": "soea_engine_constraintprog_motorconstraintprogramming_motorconstraintprogramming_resolversincrono", "callee": "ToString", "is_member_call": true, "source_file": "A:\\Unversidad\\_PRACTICAS_UNI\\CODIGO\\SOEA\\src\\SOEA.Engine.ConstraintProg\\MotorConstraintProgramming.cs", "source_location": "L322"}, {"caller_nid": "soea_engine_constraintprog_motorconstraintprogramming_motorconstraintprogramming_resolversincrono", "callee": "LogInformation", "is_member_call": true, "source_file": "A:\\Unversidad\\_PRACTICAS_UNI\\CODIGO\\SOEA\\src\\SOEA.Engine.ConstraintProg\\MotorConstraintProgramming.cs", "source_location": "L323"}, {"caller_nid": "soea_engine_constraintprog_motorconstraintprogramming_motorconstraintprogramming_resolversincrono", "callee": "LogWarning", "is_member_call": true, "source_file": "A:\\Unversidad\\_PRACTICAS_UNI\\CODIGO\\SOEA\\src\\SOEA.Engine.ConstraintProg\\MotorConstraintProgramming.cs", "source_location": "L327"}, {"caller_nid": "soea_engine_constraintprog_motorconstraintprogramming_motorconstraintprogramming_resolversincrono", "callee": "LogInformation", "is_member_call": true, "source_file": "A:\\Unversidad\\_PRACTICAS_UNI\\CODIGO\\SOEA\\src\\SOEA.Engine.ConstraintProg\\MotorConstraintProgramming.cs", "source_location": "L333"}, {"caller_nid": "soea_engine_constraintprog_motorconstraintprogramming_motorconstraintprogramming_resolversincrono", "callee": "Solve", "is_member_call": true, "source_file": "A:\\Unversidad\\_PRACTICAS_UNI\\CODIGO\\SOEA\\src\\SOEA.Engine.ConstraintProg\\MotorConstraintProgramming.cs", "source_location": "L334"}, {"caller_nid": "soea_engine_constraintprog_motorconstraintprogramming_motorconstraintprogramming_resolversincrono", "callee": "LogInformation", "is_member_call": true, "source_file": "A:\\Unversidad\\_PRACTICAS_UNI\\CODIGO\\SOEA\\src\\SOEA.Engine.ConstraintProg\\MotorConstraintProgramming.cs", "source_location": "L335"}, {"caller_nid": "soea_engine_constraintprog_motorconstraintprogramming_motorconstraintprogramming_resolversincrono", "callee": "Value", "is_member_call": true, "source_file": "A:\\Unversidad\\_PRACTICAS_UNI\\CODIGO\\SOEA\\src\\SOEA.Engine.ConstraintProg\\MotorConstraintProgramming.cs", "source_location": "L345"}, {"caller_nid": "soea_engine_constraintprog_motorconstraintprogramming_motorconstraintprogramming_resolversincrono", "callee": "TryGetValue", "is_member_call": true, "source_file": "A:\\Unversidad\\_PRACTICAS_UNI\\CODIGO\\SOEA\\src\\SOEA.Engine.ConstraintProg\\MotorConstraintProgramming.cs", "source_location": "L350"}, {"caller_nid": "soea_engine_constraintprog_motorconstraintprogramming_motorconstraintprogramming_resolversincrono", "callee": "Value", "is_member_call": true, "source_file": "A:\\Unversidad\\_PRACTICAS_UNI\\CODIGO\\SOEA\\src\\SOEA.Engine.ConstraintProg\\MotorConstraintProgramming.cs", "source_location": "L352"}, {"caller_nid": "soea_engine_constraintprog_motorconstraintprogramming_motorconstraintprogramming_resolversincrono", "callee": "Add", "is_member_call": true, "source_file": "A:\\Unversidad\\_PRACTICAS_UNI\\CODIGO\\SOEA\\src\\SOEA.Engine.ConstraintProg\\MotorConstraintProgramming.cs", "source_location": "L357"}, {"caller_nid": "soea_engine_constraintprog_motorconstraintprogramming_motorconstraintprogramming_resolversincrono", "callee": "NewGuid", "is_member_call": true, "source_file": "A:\\Unversidad\\_PRACTICAS_UNI\\CODIGO\\SOEA\\src\\SOEA.Engine.ConstraintProg\\MotorConstraintProgramming.cs", "source_location": "L358"}, {"caller_nid": "soea_engine_constraintprog_motorconstraintprogramming_motorconstraintprogramming_resolversincrono", "callee": "LogInformation", "is_member_call": true, "source_file": "A:\\Unversidad\\_PRACTICAS_UNI\\CODIGO\\SOEA\\src\\SOEA.Engine.ConstraintProg\\MotorConstraintProgramming.cs", "source_location": "L367"}, {"caller_nid": "soea_engine_constraintprog_motorconstraintprogramming_motorconstraintprogramming_resolversincrono", "callee": "AsReadOnly", "is_member_call": true, "source_file": "A:\\Unversidad\\_PRACTICAS_UNI\\CODIGO\\SOEA\\src\\SOEA.Engine.ConstraintProg\\MotorConstraintProgramming.cs", "source_location": "L370"}, {"caller_nid": "soea_engine_constraintprog_motorconstraintprogramming_motorconstraintprogramming_resolversincrono", "callee": "LogWarning", "is_member_call": true, "source_file": "A:\\Unversidad\\_PRACTICAS_UNI\\CODIGO\\SOEA\\src\\SOEA.Engine.ConstraintProg\\MotorConstraintProgramming.cs", "source_location": "L373"}]}